Term Project/CS303 Proj Phase II/hockeyasm.v
module hockey(
    input clk,
    input rst,
    
    input BTN_A,
    input BTN_B,
    
    input [1:0] DIR_A,
    input [1:0] DIR_B,
    
    input [2:0] Y_in_A,
    input [2:0] Y_in_B,

    /*output reg LEDA,
    output reg LEDB,
    output reg [4:0] LEDX,
    
    output reg [6:0] SSD7,
    output reg [6:0] SSD6,
    output reg [6:0] SSD5,
    output reg [6:0] SSD4, 
    output reg [6:0] SSD3,
    output reg [6:0] SSD2,
    output reg [6:0] SSD1,
    output reg [6:0] SSD0   */
	
	output reg [2:0] X_COORD,
	output reg [2:0] Y_COORD
);

localparam IDLE = 4'd0,
           DISP = 4'd1,
           HIT_B = 4'd2,
           HIT_A = 4'd3,
           SEND_A = 4'd4,
           SEND_B = 4'd5,
           RESP_A = 4'd6,
           RESP_B = 4'd7,
           GOAL_A = 4'd8,
           GOAL_B = 4'd9,
           ENDED = 4'd10;

// Game variables
reg [4:0] game_state;
reg [1:0] timer;
reg [2:0] score_A, score_B;
reg [1:0] current_direction;
reg turn;

// Initialize the game state and scores
initial begin
    game_state <= IDLE;
    timer <= 0;
    score_A <= 0;
    score_B <= 0;
    current_direction <= 0;
    turn <= 0;
end

// Main game logic
always @(posedge clk or posedge rst) begin
    if (rst) begin
        game_state <= IDLE;
        timer <= 0;
        score_A <= 0;
        score_B <= 0;
        current_direction <= 0;
        turn <= 0;
    end else begin
        case (game_state)
            IDLE: begin
                if (BTN_A && !BTN_B) begin
                    // BTN_A pressed, BTN_B not pressed
                    turn <= 0;
                    game_state <= DISP;
                end else if (!BTN_A && BTN_B) begin
                    // BTN_A not pressed, BTN_B pressed
                    turn <= 1;
                    game_state <= DISP;
                end
            end
            DISP: begin
                // Display scores for 1 second
                // ...

                if (timer < 2) begin
                    timer <= timer + 1;
                end else begin
                    timer <= 0;
                    if (turn == 1) begin
                        game_state <= HIT_B;
                    end else begin
                        game_state <= HIT_A;
                    end
                end
            end
            HIT_A: begin
                if (Y_in_A < 5 && BTN_A) begin
                    X_COORD <= 0; // Start from left
                    Y_COORD <= Y_in_A;
                    current_direction <= DIR_A;
                    game_state <= SEND_B;
                end
            end
            HIT_B: begin
                if (Y_in_B < 5 && BTN_B) begin
                    X_COORD <= 4; // Start from right
                    Y_COORD <= Y_in_B;
                    current_direction <= DIR_B;
                    game_state <= SEND_A;
                end
            end
            SEND_B: begin
                if (timer < 2) begin 
                    timer <= timer + 1;
                end else begin 
                    timer <= 0;
                end

                // Check for bounce and update vertical movement
                if (current_direction == 2'b01) begin // Moving up
                    if (Y_COORD == 4) begin
                        Y_COORD <= Y_COORD - 1; // Bounce down
                        current_direction <= 2'b10;
                    end    
                    else begin
                        Y_COORD <= Y_COORD + 1;
                    end
                end else if (current_direction == 2'b10) begin // Moving down
                    if (Y_COORD == 0) begin
                        Y_COORD <= Y_COORD + 1; // Bounce up
                        current_direction <= 2'b01;
                    end 
                    else begin
                        Y_COORD <= Y_COORD - 1;
                    end
                end
                if (X_COORD < 3) begin 
                    X_COORD <= X_COORD + 1;
                end else begin 
                    X_COORD <= 4;
                    game_state <= RESP_B;
                end
            end
            RESP_A: begin
                if (timer < 2) begin 
                    if (BTN_A && Y_COORD == Y_in_A) begin
                        X_COORD <= 1;
                        timer <= 0;
                        if (DIR_B == 2'b01) begin // Moving up
                            if (Y_COORD == 4) begin
                                Y_COORD <= Y_COORD - 1; // Bounce down
                                current_direction <= 2'b10;
                                game_state <= SEND_B;
                            end    
                            else begin
                                Y_COORD <= Y_COORD + 1;
                                current_direction <= DIR_A;
                                game_state <= SEND_B;
                            end
                        end else if (DIR_B == 2'b10) begin // Moving down
                                if (Y_COORD == 0) begin
                                    Y_COORD <= Y_COORD + 1; // Bounce up
                                    current_direction <= 2'b01;
                                    game_state <= SEND_B;
                                end 
                                else begin
                                    Y_COORD <= Y_COORD - 1;
                                    current_direction <= DIR_A;
                                    game_state <= SEND_B;
                                end
                        end else if (DIR_B == 2'b00) begin 
                            current_direction <= DIR_B;
                            game_state <= SEND_B;
                        end
                    end else begin
                        timer <= timer + 1;
                    end
                end else begin 
                    timer <= 0;
                    score_B <= score_B + 1;
                    game_state <= GOAL_B;
                end
            end
            SEND_A: begin
                if (timer < 2) begin 
                    timer <= timer + 1;
                end else begin 
                    timer <= 0;
                end

                // Check for bounce and update vertical movement
                if (current_direction == 2'b01) begin // Moving up
                    if (Y_COORD == 4) begin
                        Y_COORD <= Y_COORD - 1; // Bounce down
                        current_direction <= 2'b10;
                    end    
                    else begin
                        Y_COORD <= Y_COORD + 1;
                    end
                end else if (current_direction == 2'b10) begin // Moving down
                    if (Y_COORD == 0) begin
                        Y_COORD <= Y_COORD + 1; // Bounce up
                        current_direction <= 2'b01;
                    end 
                    else begin
                        Y_COORD <= Y_COORD - 1;
                    end
                end
                if (X_COORD > 1) begin 
                    X_COORD <= X_COORD - 1;
                end else begin 
                    X_COORD <= 0;
                    game_state <= RESP_A;
                end
            end
            RESP_B: begin
                if (timer < 2) begin 
                    if (Y_in_B == Y_COORD && BTN_B) begin
                        // Transition to Player B's turn
                        X_COORD <= 3;
                        timer <= 0;
                        if (DIR_B == 2'b01) begin // Moving up
                            if (Y_COORD == 4) begin
                                Y_COORD <= Y_COORD - 1; // Bounce down
                                current_direction <= 2'b10;
                                game_state <= SEND_A;
                            end    
                            else begin
                                Y_COORD <= Y_COORD + 1;
                                current_direction <= DIR_B;
                                game_state <= SEND_A;
                            end
                        end else if (DIR_B == 2'b10) begin // Moving down
                            if (Y_COORD == 0) begin
                                Y_COORD <= Y_COORD + 1; // Bounce up
                                current_direction <= 2'b01;
                                game_state <= SEND_A;
                            end 
                            else begin
                                Y_COORD <= Y_COORD - 1;
                                current_direction <= DIR_B;
                                game_state <= SEND_A;
                            end
                        end else if (DIR_B == 2'b00) begin 
                            current_direction <= DIR_A;
                            game_state <= SEND_A;
                        end
                    end else begin
                        timer <= timer + 1;
                    end
                end else begin 
                    timer <= 0;
                    score_A <= score_A + 1;
                    game_state <= GOAL_A;
                end
            end
            GOAL_A: begin
                if (timer < 2) begin 
                    timer <= timer + 1;
                end else begin 
                    timer <= 0;
                    // Check if A has won
                    if (score_A == 3) begin
                        turn <= 0;
                        game_state <= ENDED;
                    end else begin
                        game_state <= HIT_B;
                    end
                end
            end
            GOAL_B: begin
                if (timer < 2) begin 
                    timer <= timer + 1;
                end else begin 
                    timer <= 0;
                    // Check if B has won
                    if (score_B == 3) begin
                        turn <= 1;
                        game_state <= ENDED;
                    end else begin
                        // No player has won yet, continue the game
                        game_state <= HIT_A;
                    end
                end
            end
            ENDED: begin
                // Handle end of game
                // Show winner and blink LEDs
            end
            default: begin
                game_state <= IDLE;
            end
        endcase
    end
end

    // LED and SSD display logic
    // ...

endmodule

Term Project/CS303 Proj Phase II/hockeyasm_tb.v
module hockey_tb();

parameter HP = 5;       // Half period of our clock signal
parameter FP = (2*HP);  // Full period of our clock signal

reg clk, rst, BTN_A, BTN_B;
reg [1:0] DIR_A;
reg [1:0] DIR_B;
reg [2:0] Y_in_A;
reg [2:0] Y_in_B;

wire [2:0] X_COORD, Y_COORD;

// Our design-under-test is the hockey module
hockey dut(clk, rst, BTN_A, BTN_B, DIR_A, DIR_B, Y_in_A, Y_in_B, X_COORD, Y_COORD);

// Automatically cycle clock
always #HP clk = ~clk;

initial begin
    $dumpfile("hockey.vcd");
    $dumpvars(0, hockey_tb);
    $display("Simulation started.");

    clk = 0; 
    rst = 0;
    BTN_A = 0;
    BTN_B = 0;
    DIR_A = 0;
    DIR_B = 0;
    Y_in_A = 0;
    Y_in_B = 0;

    // 1- Reset the Circuit
    #FP rst = 1;
    #FP rst = 0;

    // 2- Player A starts the game
    #HP BTN_A = 1;
    #FP BTN_A = 0;
    #FP #FP #FP;

    // 3- Inputs for Player A and go to SEND_B state
    Y_in_A = 3'b010;  // Example position
    DIR_A = 2'b01;    // Example direction
    BTN_A = 1;
    #FP BTN_A = 0;
    #FP #FP #FP #FP; // Puck travels to Player B

    // 4- Inputs for Player B, wrong position, go to GOAL_A state
    Y_in_B = 3'b011;  // Different from puck's Y position
    BTN_B = 1;
    #FP BTN_B = 0;
    #FP; // Goal scored

    // 5- Check A has 3 goals, go to HIT_B state (score : 1-0)
    #FP #FP #FP;

    // 6- Inputs for Player B and go to SEND_A state
    Y_in_B = 3'b001;  // Example position
    DIR_B = 2'b10;    // Example direction
    BTN_B = 1;
    #FP BTN_B = 0;
    #FP #FP #FP #FP; // Puck travels to Player A

    // 7- Inputs for Player A, correct position, go to SEND_B state
    Y_in_A = 3'b011;  // Same as puck's Y position
    DIR_A = 2'b01;    // Example direction
    BTN_A = 1;
    #FP BTN_A = 0;
    #FP #FP #FP; // Puck travels to Player B

    // 8- Inputs for Player B, correct position, go to SEND_A state
    Y_in_B = 3'b011;  // Same as puck's Y position
    DIR_B = 2'b10;    // Example direction
    BTN_B = 1;
    #FP BTN_B = 0;
    #FP #FP #FP; // Puck travels to Player A

    // 9- Inputs for Player A, wrong position, go to GOAL_B state
    Y_in_A = 3'b010;  // Different from puck's Y position
    BTN_A = 1;
    #FP BTN_A = 0;
    #FP #FP; // Goal scored

    // 10- Check B has 3 goals, go to HIT_A state (score : 1-1)
    #FP #FP #FP;

    // 11- Inputs for Player A, go to SEND_B state
    Y_in_A = 3'b010;  // Example position
    DIR_A = 2'b01;    // Example direction
    BTN_A = 1;
    #FP BTN_A = 0;
    #FP #FP #FP #FP; // Puck travels to Player B

    // 12- Inputs for Player B, wrong position, go to GOAL_A state
    Y_in_B = 3'b011;  // Different from puck's Y position
    BTN_B = 1;
    #FP BTN_B = 0;
    #FP; // Goal scored

    // 13- Check A has 3 goals, go to HIT_B state (score : 2-1)
    #FP #FP #FP;

    // 14- Inputs for Player B, go to SEND_A state
    Y_in_B = 3'b010;  // Example position
    DIR_B = 2'b10;    // Example direction
    BTN_B = 1;
    #FP BTN_B = 0;
    #FP #FP #FP #FP; // Puck travels to Player A

    // 15- Inputs for Player A, correct position, go to SEND_B state
    Y_in_A = 3'b010;  // Same as puck's Y position
    DIR_A = 2'b01;    // Example direction
    BTN_A = 1;
    #FP BTN_A = 0;
    #FP #FP #FP; // Puck travels to Player B

    // 16- Inputs for Player B, correct position, go to SEND_A state
    Y_in_B = 3'b100;  // Same as puck's Y position
    DIR_B = 2'b10;    // Example direction
    BTN_B = 1;
    #FP BTN_B = 0;
    #FP #FP #FP; // Puck travels to Player A

    // 17- Inputs for Player A, correct position, go to SEND_B state
    Y_in_A = 3'b000;  // Same as puck's Y position
    DIR_A = 2'b01;    // Example direction
    BTN_A = 1;
    #FP BTN_A = 0;
    #FP #FP #FP; // Puck travels to Player B

    // 18- Inputs for Player B, wrong position, go to GOAL_A state
    Y_in_B = 3'b011;  // Different from puck's Y position
    BTN_B = 1;
    #FP BTN_B = 0;
    #FP; // Goal scored

    // 19- Check A has 3 goals, go to ENDED state (score : 3-1)
    #FP #FP #FP #FP #FP;

    $display("Simulation finished.");
    $finish(); // Finish simulation.
end

endmodule

Term Project/CS303 Proj Phase II/hockey.vcd
$date
	Sat Dec 30 12:27:17 2023
$end
$version
	Icarus Verilog
$end
$timescale
	1s
$end
$scope module hockey_tb $end
$var wire 3 ! Y_COORD [2:0] $end
$var wire 3 " X_COORD [2:0] $end
$var parameter 64 # FP $end
$var parameter 32 $ HP $end
$var reg 1 % BTN_A $end
$var reg 1 & BTN_B $end
$var reg 2 ' DIR_A [1:0] $end
$var reg 2 ( DIR_B [1:0] $end
$var reg 3 ) Y_in_A [2:0] $end
$var reg 3 * Y_in_B [2:0] $end
$var reg 1 + clk $end
$var reg 1 , rst $end
$scope module dut $end
$var wire 1 % BTN_A $end
$var wire 1 & BTN_B $end
$var wire 2 - DIR_A [1:0] $end
$var wire 2 . DIR_B [1:0] $end
$var wire 3 / Y_in_A [2:0] $end
$var wire 3 0 Y_in_B [2:0] $end
$var wire 1 + clk $end
$var wire 1 , rst $end
$var parameter 4 1 DISP $end
$var parameter 4 2 ENDED $end
$var parameter 4 3 GOAL_A $end
$var parameter 4 4 GOAL_B $end
$var parameter 4 5 HIT_A $end
$var parameter 4 6 HIT_B $end
$var parameter 4 7 IDLE $end
$var parameter 4 8 RESP_A $end
$var parameter 4 9 RESP_B $end
$var parameter 4 : SEND_A $end
$var parameter 4 ; SEND_B $end
$var reg 3 < X_COORD [2:0] $end
$var reg 3 = Y_COORD [2:0] $end
$var reg 2 > current_direction [1:0] $end
$var reg 5 ? game_state [4:0] $end
$var reg 3 @ score_A [2:0] $end
$var reg 3 A score_B [2:0] $end
$var reg 2 B timer [1:0] $end
$var reg 1 C turn $end
$upscope $end
$upscope $end
$enddefinitions $end
$comment Show the parameter values. $end
$dumpall
b101 ;
b100 :
b111 9
b110 8
b0 7
b10 6
b11 5
b1001 4
b1000 3
b1010 2
b1 1
b101 $
b1010 #
$end
#0
$dumpvars
0C
b0 B
b0 A
b0 @
b0 ?
b0 >
bx =
bx <
b0 0
b0 /
b0 .
b0 -
0,
0+
b0 *
b0 )
b0 (
b0 '
0&
0%
bx "
bx !
$end
#5
1+
#10
0+
1,
#15
1+
#20
0+
0,
#25
b1 ?
1+
1%
#30
0+
#35
b1 B
1+
0%
#40
0+
#45
b10 B
1+
#50
0+
#55
b11 ?
b0 B
1+
#60
0+
#65
b101 ?
b1 >
b10 !
b10 =
b0 "
b0 <
1+
1%
b1 '
b1 -
b10 )
b10 /
#70
0+
#75
b1 "
b1 <
b11 !
b11 =
b1 B
1+
0%
#80
0+
#85
b10 "
b10 <
b100 !
b100 =
b10 B
1+
#90
0+
#95
b11 "
b11 <
b10 >
b11 !
b11 =
b0 B
1+
#100
0+
#105
b111 ?
b100 "
b100 <
b10 !
b10 =
b1 B
1+
#110
0+
#115
b10 B
1+
1&
b11 *
b11 0
#120
0+
#125
b1000 ?
b1 @
b0 B
1+
0&
#130
0+
#135
b1 B
1+
#140
0+
#145
b10 B
1+
#150
0+
#155
b10 ?
b0 B
1+
#160
0+
#165
b100 ?
b1 !
b1 =
1+
1&
b10 (
b10 .
b1 *
b1 0
#170
0+
#175
b11 "
b11 <
b0 !
b0 =
b1 B
1+
0&
#180
0+
#185
b10 "
b10 <
b1 >
b1 !
b1 =
b10 B
1+
#190
0+
#195
b1 "
b1 <
b10 !
b10 =
b0 B
1+
#200
0+
#205
b110 ?
b0 "
b0 <
b11 !
b11 =
b1 B
1+
#210
0+
#215
b101 ?
b10 !
b10 =
b0 B
b1 "
b1 <
1+
1%
b11 )
b11 /
#220
0+
#225
b10 "
b10 <
b11 !
b11 =
b1 B
1+
0%
#230
0+
#235
b11 "
b11 <
b100 !
b100 =
b10 B
1+
#240
0+
#245
b111 ?
b100 "
b100 <
b10 >
b11 !
b11 =
b0 B
1+
#250
0+
#255
b100 ?
b10 !
b10 =
b11 "
b11 <
1+
1&
b11 *
b11 0
#260
0+
#265
b10 "
b10 <
b1 !
b1 =
b1 B
1+
0&
#270
0+
#275
b1 "
b1 <
b0 !
b0 =
b10 B
1+
#280
0+
#285
b110 ?
b0 "
b0 <
b1 >
b1 !
b1 =
b0 B
1+
#290
0+
#295
b1 B
1+
1%
b10 )
b10 /
#300
0+
#305
b10 B
1+
0%
#310
0+
#315
b1001 ?
b1 A
b0 B
1+
#320
0+
#325
b1 B
1+
#330
0+
#335
b10 B
1+
#340
0+
#345
b11 ?
b0 B
1+
#350
0+
#355
b101 ?
b10 !
b10 =
1+
1%
#360
0+
#365
b1 "
b1 <
b11 !
b11 =
b1 B
1+
0%
#370
0+
#375
b10 "
b10 <
b100 !
b100 =
b10 B
1+
#380
0+
#385
b11 "
b11 <
b10 >
b11 !
b11 =
b0 B
1+
#390
0+
#395
b111 ?
b100 "
b100 <
b10 !
b10 =
b1 B
1+
#400
0+
#405
b10 B
1+
1&
#410
0+
#415
b1000 ?
b10 @
b0 B
1+
0&
#420
0+
#425
b1 B
1+
#430
0+
#435
b10 B
1+
#440
0+
#445
b10 ?
b0 B
1+
#450
0+
#455
b100 ?
1+
1&
b10 *
b10 0
#460
0+
#465
b11 "
b11 <
b1 !
b1 =
b1 B
1+
0&
#470
0+
#475
b10 "
b10 <
b0 !
b0 =
b10 B
1+
#480
0+
#485
b1 "
b1 <
b1 >
b1 !
b1 =
b0 B
1+
#490
0+
#495
b110 ?
b0 "
b0 <
b10 !
b10 =
b1 B
1+
#500
0+
#505
b101 ?
b1 !
b1 =
b0 B
b1 "
b1 <
1+
1%
#510
0+
#515
b10 "
b10 <
b10 !
b10 =
b1 B
1+
0%
#520
0+
#525
b11 "
b11 <
b11 !
b11 =
b10 B
1+
#530
0+
#535
b111 ?
b100 "
b100 <
b100 !
b100 =
b0 B
1+
#540
0+
#545
b100 ?
b10 >
b11 !
b11 =
b11 "
b11 <
1+
1&
b100 *
b100 0
#550
0+
#555
b10 "
b10 <
b10 !
b10 =
b1 B
1+
0&
#560
0+
#565
b1 "
b1 <
b1 !
b1 =
b10 B
1+
#570
0+
#575
b110 ?
b0 "
b0 <
b0 !
b0 =
b0 B
1+
#580
0+
#585
b101 ?
b1 >
b1 !
b1 =
b1 "
b1 <
1+
1%
b0 )
b0 /
#590
0+
#595
b10 "
b10 <
b10 !
b10 =
b1 B
1+
0%
#600
0+
#605
b11 "
b11 <
b11 !
b11 =
b10 B
1+
#610
0+
#615
b111 ?
b100 "
b100 <
b100 !
b100 =
b0 B
1+
#620
0+
#625
b1 B
1+
1&
b11 *
b11 0
#630
0+
#635
b10 B
1+
0&
#640
0+
#645
b1000 ?
b11 @
b0 B
1+
#650
0+
#655
b1 B
1+
#660
0+
#665
b10 B
1+
#670
0+
#675
b1010 ?
b0 B
1+
