Lab3 - 16-bit Carry Lookahead Adder/CLA_4bit.v
module CLA_4bit (
    input [3:0] C,
    input [3:0] D,
    input Cin,
    input mode, // 0 --> addition , 1 --> subtraction          
    output [3:0] RES,
    output Carry
);
    wire [3:0] G, P, D_inv;
    wire [4:1] C_out;

    // Select D or ~D based on the mode
    assign D_inv = (mode == 1'b0) ? D : ~D;

    // Generate (G) and Propagate (P) signals
    assign G[0] = C[0] & D_inv[0];
    assign G[1] = C[1] & D_inv[1];
    assign G[2] = C[2] & D_inv[2];
    assign G[3] = C[3] & D_inv[3];

    assign P[0] = C[0] ^ D_inv[0];
    assign P[1] = C[1] ^ D_inv[1];
    assign P[2] = C[2] ^ D_inv[2];
    assign P[3] = C[3] ^ D_inv[3];

    // Carry calculations for each bit
    assign C_out[1] = G[0] | (P[0] & Cin);
    assign C_out[2] = G[1] | (P[1] & G[0]) | (P[1] & P[0] & Cin);
    assign C_out[3] = G[2] | (P[2] & G[1]) | (P[2] & P[1] & G[0]) | (P[2] & P[1] & P[0] & Cin);
    assign C_out[4] = G[3] | (P[3] & G[2]) | (P[3] & P[2] & G[1]) | (P[3] & P[2] & P[1] & G[0]) | (P[3] & P[2] & P[1] & P[0] & Cin);

    // Result calculation for each bit
    assign RES[0] = C[0] ^ D_inv[0] ^ Cin;
    assign RES[1] = C[1] ^ D_inv[1] ^ C_out[1];
    assign RES[2] = C[2] ^ D_inv[2] ^ C_out[2];
    assign RES[3] = C[3] ^ D_inv[3] ^ C_out[3];

    assign Carry = C_out[4];

endmodule

Lab3 - 16-bit Carry Lookahead Adder/CLA_16bit_top.v
module CLA_16bit_top (
    input [15:0] A,
    input [15:0] B,
    input mode, // 0 --> addition , 1 --> subtraction
    output [15:0] S,
    output Cout,
    output OVF
);
    wire [3:0] carry_out;
    wire overflow;

    CLA_4bit cla1 (A[3:0], B[3:0], mode, mode, S[3:0], carry_out[0]);
    CLA_4bit cla2 (A[7:4], B[7:4], carry_out[0], mode, S[7:4], carry_out[1]);
    CLA_4bit cla3 (A[11:8], B[11:8], carry_out[1], mode, S[11:8], carry_out[2]);
    CLA_4bit cla4 (A[15:12], B[15:12], carry_out[2], mode, S[15:12], carry_out[3]);

    assign Cout = carry_out[3];
    assign OVF = carry_out[2] ^ carry_out[3]; // Overflow detection

endmodule

Lab3 - 16-bit Carry Lookahead Adder/CLA_16bit_tb.v
module CLA_16bit_tb();

reg  [15:0]         A, B; // Inputs
reg                 mode;  // mode (add or subtract)
wire [15:0]         S; // result
wire                Ovf;   // Outputs are wires.
wire                Cout;

CLA_16bit_top dut(A, B, mode, S, Cout ,Ovf); // Our design-under-test.

initial begin
    //  * Our waveform is saved under this file.
    
    $dumpfile("CLA_16bit_top.vcd"); 
    
    // * Get the variables from the module.

    $dumpvars(0,CLA_16bit_tb);

    $display("Simulation started.");

    // ADDITION CASES

    // no Carry and No Overflow
    A = 16'h0007;  // 7
    B = 16'h0002;  // 2
    mode = 1'd0;   // Addition mode
    #10;           // Wait 10 time units.

    // no Carry with overflow
    A = 16'h7FFF;  // 32767
    B = 16'h0001;  // 1
    mode = 1'd0;   // Addition mode
    #10;           // Wait 10 time units.

    // with Carry no overflow
    A = 16'hFFFE;  // -2
    B = 16'h0002;  // 2
    mode = 1'd0;   // Addition mode
    #10;           // Wait 10 time units.

    // with Carry with overflow
    A = 16'h8000;  // -32768
    B = 16'h8000;  // -32768
    mode = 1'd0;   // Addition mode
    #10;           // Wait 10 time units.

    // SUBSTRACTION CASES

    // no Carry no overflow
    A = 16'h0000;  // 0
    B = 16'h0002;  // 2
    mode = 1'd1;   // Substraction mode
    #10;           // Wait 10 time units.

    // no Carry with overflow
    A = 16'h7FFF;  // 32767
    B = 16'hFFFF;  // -1
    mode = 1'd1;   // Substraction mode
    #10;           // Wait 10 time units.

    // with Carry no overflow
    A = 16'h0009;  // 9
    B = 16'h0002;  // 2
    mode = 1'd1;   // Substraction mode
    #10;           // Wait 10 time units.

    // with Carry with overflow
    A = 16'h8001;  // -32767
    B = 16'h0002;  // 2
    mode = 1'd1;   // Substraction mode
    #10;           // Wait 10 time units.

    $display("Simulation finished.");
    $finish(); // Finish simulation.
end

endmodule

Lab3 - 16-bit Carry Lookahead Adder/CLA_16bit_top.vcd
$date
	Fri Dec  1 16:04:40 2023
$end
$version
	Icarus Verilog
$end
$timescale
	1s
$end
$scope module CLA_16bit_tb $end
$var wire 16 ! S [15:0] $end
$var wire 1 " Ovf $end
$var wire 1 # Cout $end
$var reg 16 $ A [15:0] $end
$var reg 16 % B [15:0] $end
$var reg 1 & mode $end
$scope module dut $end
$var wire 16 ' A [15:0] $end
$var wire 16 ( B [15:0] $end
$var wire 1 " OVF $end
$var wire 1 & mode $end
$var wire 4 ) carry_out [3:0] $end
$var wire 16 * S [15:0] $end
$var wire 1 # Cout $end
$scope module cla1 $end
$var wire 4 + C [3:0] $end
$var wire 1 & Cin $end
$var wire 4 , D [3:0] $end
$var wire 1 & mode $end
$var wire 4 - RES [3:0] $end
$var wire 4 . P [3:0] $end
$var wire 4 / G [3:0] $end
$var wire 4 0 D_inv [3:0] $end
$var wire 1 1 Carry $end
$var wire 4 2 C_out [4:1] $end
$upscope $end
$scope module cla2 $end
$var wire 4 3 C [3:0] $end
$var wire 1 4 Cin $end
$var wire 4 5 D [3:0] $end
$var wire 1 & mode $end
$var wire 4 6 RES [3:0] $end
$var wire 4 7 P [3:0] $end
$var wire 4 8 G [3:0] $end
$var wire 4 9 D_inv [3:0] $end
$var wire 1 : Carry $end
$var wire 4 ; C_out [4:1] $end
$upscope $end
$scope module cla3 $end
$var wire 4 < C [3:0] $end
$var wire 1 = Cin $end
$var wire 4 > D [3:0] $end
$var wire 1 & mode $end
$var wire 4 ? RES [3:0] $end
$var wire 4 @ P [3:0] $end
$var wire 4 A G [3:0] $end
$var wire 4 B D_inv [3:0] $end
$var wire 1 C Carry $end
$var wire 4 D C_out [4:1] $end
$upscope $end
$scope module cla4 $end
$var wire 4 E C [3:0] $end
$var wire 1 F Cin $end
$var wire 4 G D [3:0] $end
$var wire 1 & mode $end
$var wire 4 H RES [3:0] $end
$var wire 4 I P [3:0] $end
$var wire 4 J G [3:0] $end
$var wire 4 K D_inv [3:0] $end
$var wire 1 L Carry $end
$var wire 4 M C_out [4:1] $end
$upscope $end
$upscope $end
$upscope $end
$enddefinitions $end
$comment Show the parameter values. $end
$dumpall
$end
#0
$dumpvars
b0 M
0L
b0 K
b0 J
b0 I
b0 H
b0 G
0F
b0 E
b0 D
0C
b0 B
b0 A
b0 @
b0 ?
b0 >
0=
b0 <
b0 ;
0:
b0 9
b0 8
b0 7
b0 6
b0 5
04
b0 3
b110 2
01
b10 0
b10 /
b101 .
b1001 -
b10 ,
b111 +
b1001 *
b0 )
b10 (
b111 '
0&
b10 %
b111 $
0#
0"
b1001 !
$end
#10
b111 M
1"
1F
1C
b1111 D
1=
1:
b1111 ;
14
b111 )
11
b1111 2
b1 /
b0 -
b0 6
b0 ?
b1000000000000000 !
b1000000000000000 *
b1000 H
b1110 .
b1111 7
b1111 @
b111 I
b1 0
b1 ,
b1111 +
b1111 3
b1111 <
b111 E
b1 %
b1 (
b111111111111111 $
b111111111111111 '
#20
1F
1C
b1111 D
b0 ?
1=
1:
0"
b1111 ;
1#
b0 6
1L
14
b1111 M
b1111 )
11
b1110 2
b0 -
b0 !
b0 *
b0 H
b10 /
b1100 .
b1111 I
b10 0
b10 ,
b1110 +
b1111 E
b10 %
b10 (
b1111111111111110 $
b1111111111111110 '
#30
1"
04
01
0=
0F
1#
0:
0C
b1000 )
1L
b0 2
b0 ;
b0 D
b1000 M
b1000 J
b0 -
b0 6
b0 ?
b0 !
b0 *
b0 H
b0 /
b0 .
b0 7
b0 @
b0 I
b0 0
b1000 K
b0 ,
b1000 G
b0 +
b0 3
b0 <
b1000 E
b1000000000000000 %
b1000000000000000 (
b1000000000000000 $
b1000000000000000 '
#40
0F
0C
b0 D
0=
0:
b0 ;
0"
04
0#
01
b0 )
0L
b0 M
b1 2
b1111 6
b1111 ?
b1111 7
b1111 @
b1101 .
b1111 H
b0 J
b1111 I
b1111 9
b1111 B
b1101 0
b1111 K
b1111111111111110 !
b1111111111111110 *
b1110 -
b10 ,
b0 G
b0 E
1&
b10 %
b10 (
b0 $
b0 '
#50
1"
0#
14
1=
1F
0L
11
1:
b111 )
1C
b1111 2
b1111 ;
b1111 D
b111 M
b0 -
b0 6
b0 ?
b1000000000000000 !
b1000000000000000 *
b1000 H
b0 0
b0 9
b0 B
b0 K
b0 /
b1111 .
b0 8
b1111 7
b0 A
b1111 @
b0 J
b111 I
b1111 ,
b1111 5
b1111 >
b1111 G
b1111 +
b1111 3
b1111 <
b111 E
b1111111111111111 %
b1111111111111111 (
b111111111111111 $
b111111111111111 '
#60
1#
1L
14
0"
11
1=
1F
1:
b1111 )
1C
b1001 2
b1111 ;
b1111 D
b1111 M
b1001 /
b111 -
b0 6
b0 ?
b111 !
b111 *
b0 H
b1101 0
b1111 9
b1111 B
b1111 K
b100 .
b1111 7
b1111 @
b1111 I
b10 ,
b0 5
b0 >
b0 G
b1001 +
b0 3
b0 <
b0 E
b10 %
b10 (
b1001 $
b1001 '
#70
b1000 M
1"
0F
0C
b0 D
b1111 ?
0=
0:
b0 ;
b1111 6
04
b1000 )
01
b1 2
b1111 -
b111111111111111 !
b111111111111111 *
b111 H
b1 /
b1100 .
b1000 J
b111 I
b1 +
b1000 E
b1000000000000001 $
b1000000000000001 '
